Metadata-Version: 2.1
Name: pyproject-requirements
Version: 20240601
Summary: Install dependencies from a pyproject using pip.
Author: MetaCompany, Nate Skulic
Classifier: Programming Language :: Python :: 3
Requires-Python: >=3.6
Requires-Dist: pip
Requires-Dist: toml
